laikatest_client/__init__.py
laikatest_client/lib/__init__.py
laikatest_client/lib/cache.py
laikatest_client/lib/errors.py
laikatest_client/lib/http.py
laikatest_client/lib/prompt.py
laikatest_client/lib/prompt_utils.py
laikatest_client/lib/validation.py
laikatest_client/lib/variables.py
laikatest_client-1.0.0.dist-info/licenses/LICENSE
laikatest_client-1.0.0.dist-info/METADATA
laikatest_client-1.0.0.dist-info/WHEEL
laikatest_client-1.0.0.dist-info/top_level.txt
laikatest_client-1.0.0.dist-info/RECORD
