Metadata-Version: 2.4
Name: laikatest-client
Version: 1.0.0
Summary: Python SDK for fetching LaikaTest prompt templates via API
Author: LaikaTest Team
License-Expression: MIT
Project-URL: Homepage, https://github.com/ForecloseAI/laikatest_client_py
Project-URL: Source, https://github.com/ForecloseAI/laikatest_client_py
Project-URL: Bug Reports, https://github.com/ForecloseAI/laikatest_client_py/issues
Keywords: laikatest,prompts,sdk,client,ai,llm,prompt-management
Classifier: Development Status :: 4 - Beta
Classifier: Intended Audience :: Developers
Classifier: Operating System :: OS Independent
Classifier: Programming Language :: Python :: 3
Classifier: Programming Language :: Python :: 3.7
Classifier: Programming Language :: Python :: 3.8
Classifier: Programming Language :: Python :: 3.9
Classifier: Programming Language :: Python :: 3.10
Classifier: Programming Language :: Python :: 3.11
Classifier: Topic :: Software Development :: Libraries :: Python Modules
Requires-Python: >=3.7
License-File: LICENSE
Dynamic: license-file
